nl_service_metadata_generator/__init__.py
nl_service_metadata_generator/cli.py
nl_service_metadata_generator/codelist_lookup.py
nl_service_metadata_generator/constants.py
nl_service_metadata_generator/enums.py
nl_service_metadata_generator/hvd_categories.py
nl_service_metadata_generator/metadata_generator.py
nl_service_metadata_generator/util.py
nl_service_metadata_generator/data/json/codelists.json
nl_service_metadata_generator/data/json_schema/constants.schema.json
nl_service_metadata_generator/data/json_schema/service.schema.json
nl_service_metadata_generator/data/schema/schemas.opengis.net/csw/2.0.2/profiles/apiso/1.0.0/apiso.xsd
nl_service_metadata_generator/data/schema/schemas.opengis.net/iso/19139/20070417/srv/1.0/serviceMetadata.xsd
nl_service_metadata_generator/data/schema/schemas.opengis.net/iso/19139/20070417/srv/1.0/serviceModel.xsd
nl_service_metadata_generator/data/schema/schemas.opengis.net/iso/19139/20070417/srv/1.0/srv.xsd
nl_service_metadata_generator/data/schema/standards.iso.org/ittf/PubliclyAvailableStandards/ISO_19136_Schemas/basicTypes.xsd
nl_service_metadata_generator/data/schema/standards.iso.org/ittf/PubliclyAvailableStandards/ISO_19136_Schemas/coordinateOperations.xsd
nl_service_metadata_generator/data/schema/standards.iso.org/ittf/PubliclyAvailableStandards/ISO_19136_Schemas/coordinateReferenceSystems.xsd
nl_service_metadata_generator/data/schema/standards.iso.org/ittf/PubliclyAvailableStandards/ISO_19136_Schemas/coordinateSystems.xsd
nl_service_metadata_generator/data/schema/standards.iso.org/ittf/PubliclyAvailableStandards/ISO_19136_Schemas/coverage.xsd
nl_service_metadata_generator/data/schema/standards.iso.org/ittf/PubliclyAvailableStandards/ISO_19136_Schemas/datums.xsd
nl_service_metadata_generator/data/schema/standards.iso.org/ittf/PubliclyAvailableStandards/ISO_19136_Schemas/deprecatedTypes.xsd
nl_service_metadata_generator/data/schema/standards.iso.org/ittf/PubliclyAvailableStandards/ISO_19136_Schemas/dictionary.xsd
nl_service_metadata_generator-0.3.0.dist-info/licenses/LICENSE
nl_service_metadata_generator-0.3.0.dist-info/METADATA
nl_service_metadata_generator-0.3.0.dist-info/WHEEL
nl_service_metadata_generator-0.3.0.dist-info/entry_points.txt
nl_service_metadata_generator-0.3.0.dist-info/top_level.txt
nl_service_metadata_generator-0.3.0.dist-info/RECORD
