Metadata-Version: 2.4
Name: nl-service-metadata-generator
Version: 0.3.0
Summary: CLI applicatie voor het genereren van service metadata die voldoet aan het Nederlands metadata profiel op ISO 19119 voor services versie 2.1.0 - https://docs.geostandaarden.nl/md/mdprofiel-iso19119/
License: MIT
Project-URL: repository, https://github.com/PDOK/nl-service-metadata-generator
Keywords: ngr,pdok,iso19119,nl-metadata-profiel,metadata,cli
Classifier: Programming Language :: Python :: 3
Classifier: Programming Language :: Python :: 3 :: Only
Classifier: Programming Language :: Python :: 3.10
Requires-Python: >=3.8.10
License-File: LICENSE
Requires-Dist: Click~=8.1
Requires-Dist: Jinja2~=3.1
Requires-Dist: lxml~=4.9
Requires-Dist: jsonschema~=4.17
Provides-Extra: dev
Requires-Dist: black; extra == "dev"
Requires-Dist: autoflake; extra == "dev"
Requires-Dist: isort; extra == "dev"
Dynamic: license-file
